setup.py
graybit_sync/__init__.py
graybit_sync.egg-info/PKG-INFO
graybit_sync.egg-info/SOURCES.txt
graybit_sync.egg-info/dependency_links.txt
graybit_sync.egg-info/not-zip-safe
graybit_sync.egg-info/top_level.txt