Metadata-Version: 1.0
Name: graybit-sync
Version: 1.0.0
Summary: Graybit blockchain sync module
Home-page: http://github.com/graybit/graybit-sync
Author: Graybit
Author-email: hash@graybit.org
License: MIT
Platform: UNKNOWN
